setup.py
dubi/__init__.py
dubi/__main__.py
dubi/env_conf.py
dubi/info.py
dubi/input_util.py
dubi/version_util.py
dubi/zcy_action.py
dubi/zcy_context.py
dubi/zcy_env.py
dubi/zcy_exception.py
dubi/zcy_method.py
dubi/zcy_parser.py
dubi/zcy_provider.py
dubi/zcy_service.py
dubi.egg-info/PKG-INFO
dubi.egg-info/SOURCES.txt
dubi.egg-info/dependency_links.txt
dubi.egg-info/entry_points.txt
dubi.egg-info/requires.txt
dubi.egg-info/top_level.txt