Metadata-Version: 1.0
Name: dubi
Version: 1.1.5
Summary: Dubbo Invoke Tool
Home-page: https://git.cai-inc.com/liangchenhao/zcy-tool
Author: Thare
Author-email: liangchenhao@cai-inc.com
License: MIT Licence
Keywords: pip,dubbo,invoke,zcy
Platform: any
